MANIFEST.in
README.txt
setup.cfg
setup.py
Products/__init__.py
Products.qPloneDropDownMenu.egg-info/PKG-INFO
Products.qPloneDropDownMenu.egg-info/SOURCES.txt
Products.qPloneDropDownMenu.egg-info/dependency_links.txt
Products.qPloneDropDownMenu.egg-info/entry_points.txt
Products.qPloneDropDownMenu.egg-info/namespace_packages.txt
Products.qPloneDropDownMenu.egg-info/not-zip-safe
Products.qPloneDropDownMenu.egg-info/requires.txt
Products.qPloneDropDownMenu.egg-info/top_level.txt
Products/qPloneDropDownMenu/DropDownMenuTool.py
Products/qPloneDropDownMenu/HISTORY.txt
Products/qPloneDropDownMenu/README.txt
Products/qPloneDropDownMenu/__init__.py
Products/qPloneDropDownMenu/config.py
Products/qPloneDropDownMenu/configure.zcml
Products/qPloneDropDownMenu/profiles.zcml
Products/qPloneDropDownMenu/setuphandlers.py
Products/qPloneDropDownMenu/skins.zcml
Products/qPloneDropDownMenu/tool.gif
Products/qPloneDropDownMenu/utils.py
Products/qPloneDropDownMenu/browser/__init__.py
Products/qPloneDropDownMenu/browser/configure.zcml
Products/qPloneDropDownMenu/browser/interfaces.py
Products/qPloneDropDownMenu/browser/sections.pt
Products/qPloneDropDownMenu/browser/views.py
Products/qPloneDropDownMenu/browser/templates/prefs_dropdownmenu_edit_form.pt
Products/qPloneDropDownMenu/profiles/default/browserlayer.xml
Products/qPloneDropDownMenu/profiles/default/controlpanel.xml
Products/qPloneDropDownMenu/profiles/default/cssregistry.xml
Products/qPloneDropDownMenu/profiles/default/import_steps.xml
Products/qPloneDropDownMenu/profiles/default/metadata.xml
Products/qPloneDropDownMenu/profiles/default/qplonedropdownmenu_various.txt
Products/qPloneDropDownMenu/profiles/default/skins.xml
Products/qPloneDropDownMenu/profiles/default/toolset.xml
Products/qPloneDropDownMenu/skins/qPloneDropDownMenu/csshover.htc.dtml
Products/qPloneDropDownMenu/skins/qPloneDropDownMenu/csshover.htc.dtml.metadata
Products/qPloneDropDownMenu/skins/qPloneDropDownMenu/csshover_save.cpy
Products/qPloneDropDownMenu/skins/qPloneDropDownMenu/csshover_save.cpy.metadata
Products/qPloneDropDownMenu/skins/qPloneDropDownMenu/drop_down.css.dtml
Products/qPloneDropDownMenu/skins/qPloneDropDownMenu/prefs_csshover_edit_form.cpt
Products/qPloneDropDownMenu/skins/qPloneDropDownMenu/prefs_csshover_edit_form.cpt.metadata
Products/qPloneDropDownMenu/skins/qPloneDropDownMenu/qplonedropdownmenu.gif
