Metadata-Version: 1.0
Name: Products.qPloneDropDownMenu
Version: 3.0
Summary: The product allows Plone websites to update multilevel portal dropdown menu
Home-page: http://quintagroup.com/services/plone-development/products/plone-drop-down-menu
Author: Quintagroup
Author-email: support@quintagroup.com
License: GPL
Keywords: plone dropdown menu
Platform: UNKNOWN
Classifier: Programming Language :: Python
Classifier: Topic :: Software Development :: Libraries :: Python Modules
